[1,["1diBb/NQVJ6IS46BBp543c@f9941","1diBb/NQVJ6IS46BBp543c@6c48a","22Raius2FDGbp0MqgSC3nm@6c48a","2be8QbLaNDa6ZXk22UFIBm@6c48a","2dhyMwZr9DSqgZJnlObx9w@6c48a","5eepgdWWFGsoURgg1CeJbs@6c48a","80OPQFyJNGa7txEn//g4HA@6c48a","a9uQ35MyVArZaNPd/lw9Ge@6c48a","22Raius2FDGbp0MqgSC3nm@f9941","d6tBbapvBAbqV7Kqxy/ZKr","2be8QbLaNDa6ZXk22UFIBm@f9941","a9uQ35MyVArZaNPd/lw9Ge@f9941","80OPQFyJNGa7txEn//g4HA@f9941","5eepgdWWFGsoURgg1CeJbs@f9941","1anAZ68WxJJI4lO11REQ6D","c4TuyAe29Lg6d8sx02vcPD","2dhyMwZr9DSqgZJnlObx9w@f9941","fexSm7YBVE3r/c8im5NzwI@f9941","d6rwaShppF/rOwgZHaevBs","8eVXfeEslAG7WAJa2RURWG","fexSm7YBVE3r/c8im5NzwI@6c48a"],["node","_textureSource","_spriteFrame","targetInfo","_parent","_cameraComponent","root","source","scene","asset","_font","_normalSprite","_bgm"],["cc.SpriteFrame",["cc.Widget",["_alignFlags","_originalWidth","_originalHeight","_alignMode","_right","_top","_bottom","_verticalCenter","_isAbsVerticalCenter","_left","_isAbsTop","_isAbsBottom","node"],-9,1],["cc.Node",["_name","_layer","_id","_active","_objFlags","__editorExtras__","_components","_parent","_lpos","_children","_prefab"],-3,12,1,5,2,4],["cc.Node",["_name","_layer","_active","_id","_components","_children","_parent","_lpos"],-1,9,2,1,5],["cc.UITransform",["node","_contentSize","_anchorPoint"],3,1,5,5],["cc.Sprite",["_sizeMode","_type","node","_spriteFrame"],1,1,6],["cc.PrefabInfo",["fileId","root","instance","asset","targetOverrides","nestedPrefabInstanceRoots"],2,1,4,6,9,2],["cc.SceneAsset",["_name"],2],["cc.Canvas",["node","_cameraComponent"],3,1,1],["cc.Mask",["_alphaThreshold","node"],2,1],["cc.UIOpacity",["node"],3,1],["cc.LabelOutline",["node"],3,1],["cc.RenderRoot2D",["_name","node"],2,1],["cc.PrefabInstance",["fileId","propertyOverrides"],2,9],["CCPropertyOverrideInfo",["value","propertyPath","targetInfo"],1,1],["CCPropertyOverrideInfo",["propertyPath","targetInfo","value"],2,1,8],["cc.TargetInfo",["localID"],2],["cc.Scene",["_name","_children","_prefab","_globals"],2,2,4,4],["cc.TargetOverrideInfo",["propertyPath","source","target","targetInfo"],2,1,1,4],["cc.SceneGlobals",["ambient","shadows","_skybox","fog","octree"],3,4,4,4,4,4],["cc.AmbientInfo",["_skyIllumLDR","_skyColorHDR","_skyColorLDR"],2,5,5],["cc.ShadowsInfo",[],3],["cc.SkyboxInfo",[],3],["cc.FogInfo",["_fogColor"],3,5],["cc.OctreeInfo",[],3],["cc.Camera",["_projection","_priority","_fov","_orthoHeight","_near","_far","_visibility","node","_color"],-4,1,5],["cc.ProgressBar",["_totalLength","_progress","node","_barSprite"],1,1,1],["cc.Label",["_srcBlendFactor","_string","_actualFontSize","_isSystemFontUsed","_underlineHeight","node"],-2,1],["cc.Button",["node"],3,1],["cc.Animation",["node","_clips"],3,1,3],["d337bwICvBEfoS96A5SE+t/",["node","_animTransition","_pbLoading","_lbLoading","_btnStart","loadingBar","loadingPage","landingPage","loadingText"],3,1,1,1,1,1,1,1,1,1]],[[4,0,1,1],[10,0,1],[2,0,1,7,6,8,3],[5,2,3,1],[3,0,1,6,4,3],[15,0,1,2,2],[3,0,1,6,5,4,3],[3,0,1,6,4,7,3],[4,0,1],[4,0,1,2,1],[5,0,2,3,2],[5,1,0,2,3],[16,0,2],[7,0,2],[2,0,1,2,9,6,8,4],[2,0,1,7,9,6,8,3],[2,0,3,1,7,6,8,4],[2,4,5,7,10,3],[2,0,1,7,6,3],[3,0,1,5,4,7,3],[3,0,2,1,6,5,4,4],[3,0,3,5,4,3],[8,0,1,1],[9,0,1,2],[1,0,7,8,3,12,5],[1,0,9,4,5,6,10,11,1,2,12,10],[1,0,9,4,5,6,7,8,1,2,3,12,11],[1,0,3,12,3],[1,0,1,2,12,4],[1,0,5,6,1,2,12,6],[1,0,4,1,2,3,12,6],[1,0,12,2],[11,0,1],[12,0,1,2],[6,0,1,2,3,2],[6,0,4,5,2],[13,0,1,2],[14,0,1,2,3],[17,0,1,2,3,2],[18,0,1,2,3,2],[19,0,1,2,3,4,1],[20,0,1,2,2],[21,1],[22,1],[23,0,1],[24,1],[25,0,1,2,3,4,5,6,7,8,8],[26,0,1,2,3,3],[27,0,1,2,3,4,5,6],[28,0,1],[29,0,1,1],[30,0,1,2,3,4,5,6,7,8,1]],[[[{"name":"Start-Button","rect":{"x":0,"y":0,"width":305,"height":124},"offset":{"x":0,"y":0},"originalSize":{"width":305,"height":124},"rotated":false,"capInsets":[0,0,0,0],"packable":true}],[0],0,[0],[1],[1]],[[{"name":"Loading BKG","rect":{"x":0,"y":0,"width":720,"height":1280},"offset":{"x":0,"y":0},"originalSize":{"width":720,"height":1280},"rotated":false,"capInsets":[0,0,0,0],"packable":true}],[0],0,[0],[1],[2]],[[{"name":"Loading...","rect":{"x":0,"y":0,"width":194,"height":46},"offset":{"x":0,"y":0},"originalSize":{"width":194,"height":46},"rotated":false,"capInsets":[0,0,0,0],"packable":true}],[0],0,[0],[1],[3]],[[{"name":"slice_Loading-back_00","rect":{"x":0,"y":0,"width":725,"height":73},"offset":{"x":0,"y":0},"originalSize":{"width":725,"height":73},"rotated":false,"capInsets":[0,0,0,0],"packable":true}],[0],0,[0],[1],[4]],[[{"name":"Brand-Logo","rect":{"x":0,"y":0,"width":458,"height":299},"offset":{"x":0,"y":0},"originalSize":{"width":458,"height":299},"rotated":false,"capInsets":[0,0,0,0],"packable":true}],[0],0,[0],[1],[5]],[[{"name":"Landing-bkg","rect":{"x":0,"y":0,"width":720,"height":603},"offset":{"x":0,"y":0},"originalSize":{"width":720,"height":603},"rotated":false,"capInsets":[0,0,0,0],"packable":true}],[0],0,[0],[1],[6]],[[{"name":"Landing-bkg (2)","rect":{"x":0,"y":0,"width":720,"height":1280},"offset":{"x":0,"y":0},"originalSize":{"width":720,"height":1280},"rotated":false,"capInsets":[0,0,0,0],"packable":true}],[0],0,[0],[1],[7]],[[[13,"splash"],[14,"Canvas",1,"6d/0ih+ChNiJ1gbuoawKEh",[-7,-8,-9,-10],[[[22,-2,-1],-3,[23,0,-4],[1,-5],[0,-6,[5,720,1280]]],4,1,4,4,4],[1,360,640,0]],[19,"loadingBar",1,[-14,-15,-16,-17],[[24,2,-2.5,false,1,-11],[1,-12],[0,-13,[5,600,60]]],[1,0,-250,0]],[6,"loadingPage",1,1,[-19,2,-20],[[8,-18]]],[15,"progressBar",1,2,[-25],[[[25,40,20,20,0.25,0.25,false,false,520,30,-21],-22,[1,-23],[0,-24,[5,560,30]]],4,1,4,4],[1,0,-300,0]],[16,"lblLoading",false,1,2,[[-26,[26,2,23,120,-63.5,38.5,-4.166666666666666,false,435,15,1,-27],[32,-28],[1,-29],[0,-30,[5,61.66,54.4]]],1,4,4,4,4],[1,0,-249.99999999999997,0]],[20,"landingPage",false,1,1,[-32,-33,-34],[[8,-31]]],[6,"bg",1,1,[-38],[[27,45,1,-35],[1,-36],[0,-37,[5,720,1280]]]],[4,"imgBg",1,7,[[10,0,-39,0],[28,45,768,1270,-40],[1,-41],[0,-42,[5,720,1280]]]],[2,"bg",1,2,[[-43,[29,45,300,-300,600,100,-44],[1,-45],[0,-46,[5,600,60]]],1,4,4,4],[1,0,-300,0]],[2,"bar",1,4,[[-47,[30,13,120,435,15,0,-48],[1,-49],[9,-50,[5,0,30],[0,0,0.5]]],1,4,4,4],[1,-280,0,0]],[21,"RenderRoot2D","8884PGSUFNbY3lcqcpqGVr",[-54],[[33,"RenderRoot2D",-51],[9,-52,[5,720,1280],[0,0,0]],[31,45,-53]]],[2,"Main Camera",1,1,[[-55,[1,-56],[0,-57,[5,0,0]]],1,4,4],[1,0,0,1000]],[17,0,null,3,[34,"fcyi2adCZEYrvs4VDpkkdF",-62,[36,"941IZnANBAQY6cOUbYjAM8",[[37,"titleHowToPlay",["_name"],-58],[5,["_lpos"],-59,[1,0,0,0]],[5,["_lrot"],-60,[3,0,0,0,1]],[5,["_euler"],-61,[1,0,0,0]]]],1]],[12,["fcyi2adCZEYrvs4VDpkkdF"]],[7,"loadingText",1,2,[[0,-63,[5,194,46]],[3,-64,2]],[1,0,-240,0]],[2,"btnStart",1,3,[[[0,-65,[5,305,124]],-66,[10,2,-67,3]],4,1,4],[1,0,-560,1000]],[18,"Controller",1,11,[[-68,[1,-69],[0,-70,[5,0,0]]],1,4,4]],[38,"splash",[1,11],[35,"3900653a-9ab0-405a-8b07-7521677df344",[[39,["popUpBehindLayer"],-71,13,[12,["33SpXxeqRBt5dV2EqH0u0Y"]]]],[13]],[40,[41,0.78125,[2,0.2,0.5019607843137255,0.8,0.520833125],[2,0.2,0.5019607843137255,0.8,0.520833125]],[42],[43],[44,[4,4292993505]],[45]]],[4,"Bg2",1,6,[[0,-72,[5,720,1280]],[3,-73,4]]],[7,"Bg",1,6,[[0,-74,[5,720,603]],[3,-75,5]],[1,0,-400,0]],[4,"imgLogo",1,6,[[0,-76,[5,458,299]],[3,-77,6]]],[46,0,-1,60,640,0.1,4096,4294967295,12,[4,4278190080]],[11,1,0,9],[11,1,0,10],[47,560,0,4,24],[48,1,"0%",40,false,0,5],[49,16],[50,1,[7,8]],[51,17,28,25,26,27,23,3,6,15]],0,[0,5,22,0,0,1,0,-2,28,0,0,1,0,0,1,0,0,1,0,-1,12,0,-2,7,0,-3,3,0,-4,6,0,0,2,0,0,2,0,0,2,0,-1,9,0,-2,4,0,-3,5,0,-4,15,0,0,3,0,-1,13,0,-3,16,0,0,4,0,-2,25,0,0,4,0,0,4,0,-1,10,0,-1,26,0,0,5,0,0,5,0,0,5,0,0,5,0,0,6,0,-1,19,0,-2,20,0,-3,21,0,0,7,0,0,7,0,0,7,0,-1,8,0,0,8,0,0,8,0,0,8,0,0,8,0,-1,23,0,0,9,0,0,9,0,0,9,0,-1,24,0,0,10,0,0,10,0,0,10,0,0,11,0,0,11,0,0,11,0,-1,17,0,-1,22,0,0,12,0,0,12,0,3,14,0,3,14,0,3,14,0,3,14,0,6,13,0,0,15,0,0,15,0,0,16,0,-2,27,0,0,16,0,-1,29,0,0,17,0,0,17,0,7,29,0,0,19,0,0,19,0,0,20,0,0,20,0,0,21,0,0,21,0,8,18,1,4,18,2,4,3,11,4,18,77],[0,0,0,0,0,0,0,0,0,23,24,26,27,29],[2,9,2,2,2,2,2,-1,-2,2,2,10,11,12],[8,9,10,0,11,12,13,14,15,16,17,18,0,19]],[[{"name":"slice_Loading-front_00","rect":{"x":0,"y":0,"width":547,"height":38},"offset":{"x":0,"y":0},"originalSize":{"width":547,"height":38},"rotated":false,"capInsets":[0,0,0,0],"packable":true}],[0],0,[0],[1],[20]]]]
